[
    {
        "id":"1",
        "Title": "Avatar",
        "Poster": "media/avatar.jpg",
        "Year": "2009",
        "Type": "movie"
    },
    {
        "id":"2",
        "Title": "Titanic",
        "Poster": "media/titanic.jpg",
        "Year": "1997",
        "Type": "movie"
    },
    {
        "id":"3",
        "Title": "Star Wars: The force Awekens",
        "Poster": "media/star_wars_the_force_awekens.jpg",
        "Year": "2015",
        "Type": "movie"
    },
    {
        "id":"4",
        "Title": "Avengers Infinity War",
        "Poster": "media/avengers_infiniti_war.jpg",
        "amount": "$2,048,359,754",
        "Year": "2018",
        "Type": "movie"
    },
    {
        "id":"5",
        "Title": "Jurassic World",
        "Poster": "media/jurassic_world.jpg",
        "Year": "2015",
        "Type": "movie"
    }
]